cflr/__init__.py
cflr/__main__.py
cflr/cli.py
cflr/sso.py
cflr-0.0.1.dist-info/LICENSE.md
cflr-0.0.1.dist-info/METADATA
cflr-0.0.1.dist-info/WHEEL
cflr-0.0.1.dist-info/entry_points.txt
cflr-0.0.1.dist-info/top_level.txt
cflr-0.0.1.dist-info/RECORD
