Metadata-Version: 2.1
Name: cflr
Version: 0.0.1
Summary: A Cloudflare Admin CLI.
Author-email: James Deane <dev@jwdeane.com>
Project-URL: homepage, https://github.com/25thhour/cflr.dev
Project-URL: issues, https://github.com/25thhour/cflr.dev/issues
Keywords: cloudflare,cli
Classifier: Programming Language :: Python :: 3.11
Classifier: License :: OSI Approved :: MIT License
Classifier: Operating System :: OS Independent
Requires-Python: >=3.11
License-File: LICENSE.md
Requires-Dist: httpx
Requires-Dist: pydantic
Requires-Dist: questionary
Requires-Dist: typer[all]
Provides-Extra: dev
Requires-Dist: black ; extra == 'dev'
Requires-Dist: ruff ; extra == 'dev'
Requires-Dist: pytest ; extra == 'dev'
